pilgram2/_1977.py
pilgram2/__init__.py
pilgram2/aden.py
pilgram2/amaro.py
pilgram2/ashby.py
pilgram2/brannan.py
pilgram2/brooklyn.py
pilgram2/charmes.py
pilgram2/clarendon.py
pilgram2/crema.py
pilgram2/css/__init__.py
pilgram2/css/blending/__init__.py
pilgram2/css/blending/alpha.py
pilgram2/css/blending/color.py
pilgram2/css/blending/color_burn.py
pilgram2/css/blending/color_dodge.py
pilgram2/css/blending/darken.py
pilgram2/css/blending/difference.py
pilgram2/css/blending/exclusion.py
pilgram2/css/blending/hard_light.py
pilgram2/css/blending/hue.py
pilgram2/css/blending/lighten.py
pilgram2/css/blending/multiply.py
pilgram2/css/blending/nonseparable.py
pilgram2/css/blending/normal.py
pilgram2/css/blending/overlay.py
pilgram2/css/blending/screen.py
pilgram2/css/blending/soft_light.py
pilgram2/css/blending/tests/__init__.py
pilgram2/css/blending/tests/helpers/__init__.py
pilgram2/css/blending/tests/helpers/alpha_support.py
pilgram2/css/blending/tests/test_alpha.py
pilgram2/css/blending/tests/test_color.py
pilgram2/css/blending/tests/test_color_burn.py
pilgram2/css/blending/tests/test_color_dodge.py
pilgram2/css/blending/tests/test_darken.py
pilgram2/css/blending/tests/test_difference.py
pilgram2/css/blending/tests/test_exclusion.py
pilgram2/css/blending/tests/test_hard_light.py
pilgram2/css/blending/tests/test_hue.py
pilgram2/css/blending/tests/test_lighten.py
pilgram2/css/blending/tests/test_multiply.py
pilgram2/css/blending/tests/test_nonseparable.py
pilgram2/css/blending/tests/test_normal.py
pilgram2/css/blending/tests/test_overlay.py
pilgram2/css/blending/tests/test_screen.py
pilgram2/css/blending/tests/test_soft_light.py
pilgram2/css/brightness.py
pilgram2/css/contrast.py
pilgram2/css/grayscale.py
pilgram2/css/hue_rotate.py
pilgram2/css/saturate.py
pilgram2/css/sepia.py
pilgram2/css/tests/__init__.py
pilgram2/css/tests/test_brightness.py
pilgram2/css/tests/test_contrast.py
pilgram2/css/tests/test_grayscale.py
pilgram2/css/tests/test_hue_rotate.py
pilgram2-2.0.9.dist-info/WHEEL
pilgram2-2.0.9.dist-info/METADATA
pilgram2-2.0.9.dist-info/RECORD
