Metadata-Version: 2.3
Name: pilgram2
Version: 2.0.9
Summary: library for instagram filters
Keywords: pillow,instagram,instagram-filters,css-filters,image-blending,blend-modes,image-processing,data-augmentation
Author: Michael G, Akiomi Kamakura
Author-email: Michael G <me@mgineer85.de>, Akiomi Kamakura <akiomik@gmail.com>
License:                                  Apache License
Classifier: License :: OSI Approved :: Apache Software License
Classifier: Operating System :: OS Independent
Classifier: Programming Language :: Python :: 3
Classifier: Programming Language :: Python :: 3.10
Classifier: Programming Language :: Python :: 3.11
Classifier: Programming Language :: Python :: 3.12
Classifier: Programming Language :: Python :: 3.13
Classifier: Programming Language :: Python :: 3.14
Classifier: Topic :: Multimedia :: Graphics
Classifier: Topic :: Software Development :: Libraries :: Python Modules
Requires-Dist: numpy>=2.0.1
Requires-Dist: pillow>=10.0.0
Maintainer: Michael G
Maintainer-email: Michael G <me@mgineer85.de>
Requires-Python: >=3.10
Project-URL: Bug Tracker, https://github.com/mgineer85/pilgram2/issues
Project-URL: Homepage, https://github.com/mgineer85/pilgram2
Project-URL: Repository, https://github.com/mgineer85/pilgram2
